CHANGES.txt
COPYRIGHT.txt
LICENSE.txt
README.txt
TODO.txt
bootstrap.py
buildout.cfg
setup.py
src/megrok/__init__.py
src/megrok.traject.egg-info/PKG-INFO
src/megrok.traject.egg-info/SOURCES.txt
src/megrok.traject.egg-info/dependency_links.txt
src/megrok.traject.egg-info/entry_points.txt
src/megrok.traject.egg-info/namespace_packages.txt
src/megrok.traject.egg-info/not-zip-safe
src/megrok.traject.egg-info/requires.txt
src/megrok.traject.egg-info/top_level.txt
src/megrok/traject/__init__.py
src/megrok/traject/components.py
src/megrok/traject/directive.py
src/megrok/traject/ftesting.zcml
src/megrok/traject/interfaces.py
src/megrok/traject/meta.py
src/megrok/traject/meta.zcml
src/megrok/traject/ftests/__init__.py
src/megrok/traject/ftests/test_traject_functional.py
src/megrok/traject/ftests/traject/__init__.py
src/megrok/traject/ftests/traject/classmethod.py
src/megrok/traject/ftests/traject/deepertraject.py
src/megrok/traject/ftests/traject/geturl.py
src/megrok/traject/ftests/traject/model.py
src/megrok/traject/ftests/traject/modelclassmethod.py
src/megrok/traject/ftests/traject/notfound.py
src/megrok/traject/ftests/traject/root.py
src/megrok/traject/ftests/traject/traject.py